MANIFEST.in
README.rst
setup.py
c/_jithon.c
c/jithon.c
c/jithon.h
c/port.c
c/port.h
c/ios/wkwebview.mm
c/v8/v8.cc
jithon/__init__.py
jithon.egg-info/PKG-INFO
jithon.egg-info/SOURCES.txt
jithon.egg-info/dependency_links.txt
jithon.egg-info/top_level.txt