Metadata-Version: 1.1
Name: jithon
Version: 0.0.1
Summary: JIT module for python.
Home-page: http://github.com/ibelie/jithon
Author: joungtao
Author-email: joungtao@gmail.com
License: MIT License
Keywords: JIT,javascript,v8,WKWebView,jithon
Platform: UNKNOWN
Classifier: Development Status :: 3 - Alpha
Classifier: Environment :: Console
Classifier: Natural Language :: English
Classifier: Operating System :: OS Independent
Classifier: License :: OSI Approved :: MIT License
Classifier: Intended Audience :: Developers
Classifier: Intended Audience :: Science/Research
Classifier: Intended Audience :: Education
Classifier: Topic :: Software Development :: Libraries
Classifier: Programming Language :: Python :: 2.7
Classifier: Programming Language :: Python :: 3.5
